cooking_with_gas/__init__.py
cooking_with_gas/gas.py
cooking_with_gas-0.0.3.dist-info/LICENSE
cooking_with_gas-0.0.3.dist-info/METADATA
cooking_with_gas-0.0.3.dist-info/WHEEL
cooking_with_gas-0.0.3.dist-info/top_level.txt
cooking_with_gas-0.0.3.dist-info/RECORD
