Metadata-Version: 2.1
Name: cooking-with-gas
Version: 0.0.3
Summary: A simple wrapper to make it easier to use the Google Apps Script API.
Author-email: Harry Boyd <hboyd255@gmail.com>
License: Copyright 2024 Harry Boyd
Project-URL: Homepage, https://github.com/HBoyd255/cooking-with-gas/
Classifier: Programming Language :: Python :: 3
Classifier: License :: OSI Approved :: MIT License
Classifier: Operating System :: OS Independent
License-File: LICENSE
Requires-Dist: requests
